__init__.py
long_banking_system/__init__.py
long_banking_system/account.py
long_banking_system/admin.py
long_banking_system/consts.py
long_banking_system/interface.py
long_banking_system/main.py
long_banking_system/messages.py
long_banking_system/models.py
long_banking_system/services.py
long_banking_system/sorts.py
long_banking_system/transactions.py
long_banking_system/utils.py
long_banking_system-0.0.1.dist-info/LICENSE
long_banking_system-0.0.1.dist-info/METADATA
long_banking_system-0.0.1.dist-info/WHEEL
long_banking_system-0.0.1.dist-info/top_level.txt
long_banking_system-0.0.1.dist-info/RECORD
