Metadata-Version: 2.1
Name: long_banking_system
Version: 0.0.1
Summary: Simple Online Banking System
Author-email: Long_Chau_Do <dolong2110@gmail.com>
Project-URL: Homepage, https://github.com/dolong2110/long-banking-system
Project-URL: Issues, https://github.com/dolong2110/long-banking-system/issues
Classifier: Programming Language :: Python :: 3
Classifier: License :: OSI Approved :: MIT License
Classifier: Operating System :: OS Independent
Requires-Python: >=3.8
License-File: LICENSE
